terminal_spinner/__init__.py
terminal_spinner/spinner.py
terminal_spinner-0.0.1.dist-info/METADATA
terminal_spinner-0.0.1.dist-info/WHEEL
terminal_spinner-0.0.1.dist-info/top_level.txt
terminal_spinner-0.0.1.dist-info/RECORD
