Metadata-Version: 2.1
Name: terminal_spinner
Version: 0.0.1
Summary: A simple terminal spinner for Python
Home-page: https://github.com/ASanchz85/spinner_shell_python
Author: Antonio Sánchez
